{
    "sourceFile": "package.json",
    "activeCommit": 0,
    "commits": [
        {
            "activePatchIndex": 1,
            "patches": [
                {
                    "date": 1749928714177,
                    "content": "Index: \n===================================================================\n--- \n+++ \n"
                },
                {
                    "date": 1749928792989,
                    "content": "Index: \n===================================================================\n--- \n+++ \n@@ -0,0 +1,103 @@\n+{\n+  \"name\": \"supauth\",\n+  \"description\": \"Supauth - Open Source Authentication Kit with Next.js, React, Supabase, and shadcn/ui\",\n+  \"version\": \"1.0.0\",\n+  \"private\": false,\n+  \"license\": \"MIT\",\n+  \"repository\": {\n+    \"type\": \"git\",\n+    \"url\": \"https://github.com/asim1801/supa-auth-nextjs\"\n+  },\n+  \"homepage\": \"https://asim1801.github.io/supa-auth-nextjs\",\n+  \"keywords\": [\n+    \"authentication\",\n+    \"nextjs\",\n+    \"react\",\n+    \"supabase\",\n+    \"shadcn\",\n+    \"open-source\",\n+    \"typescript\",\n+    \"tailwindcss\"\n+  ],\n+  \"author\": \"Supauth Contributors\",\n+  \"scripts\": {\n+    \"dev\": \"next dev\",\n+    \"build\": \"next build\",\n+    \"start\": \"next start\",\n+    \"lint\": \"next lint\",\n+    \"setup\": \"node scripts/setup.js\",\n+    \"migrate\": \"npx supabase db push\",\n+    \"db:generate-types\": \"npx supabase gen types typescript --local > src/types/database.types.ts\",\n+    \"export\": \"next build && next export\",\n+    \"deploy\": \"npm run build && gh-pages -d out\",\n+    \"predeploy\": \"npm run build\",\n+    \"postinstall\": \"echo '✅ Installation complete! Run npm run dev to start the development server.'\"\n+  },\n+  \"dependencies\": {\n+    \"@hookform/resolvers\": \"^3.9.0\",\n+    \"@radix-ui/react-accordion\": \"^1.2.0\",\n+    \"@radix-ui/react-alert-dialog\": \"^1.1.1\",\n+    \"@radix-ui/react-aspect-ratio\": \"^1.1.0\",\n+    \"@radix-ui/react-avatar\": \"^1.1.0\",\n+    \"@radix-ui/react-checkbox\": \"^1.1.1\",\n+    \"@radix-ui/react-collapsible\": \"^1.1.0\",\n+    \"@radix-ui/react-context-menu\": \"^2.2.1\",\n+    \"@radix-ui/react-dialog\": \"^1.1.2\",\n+    \"@radix-ui/react-dropdown-menu\": \"^2.1.1\",\n+    \"@radix-ui/react-hover-card\": \"^1.1.1\",\n+    \"@radix-ui/react-label\": \"^2.1.0\",\n+    \"@radix-ui/react-menubar\": \"^1.1.1\",\n+    \"@radix-ui/react-navigation-menu\": \"^1.2.0\",\n+    \"@radix-ui/react-popover\": \"^1.1.1\",\n+    \"@radix-ui/react-progress\": \"^1.1.0\",\n+    \"@radix-ui/react-radio-group\": \"^1.2.0\",\n+    \"@radix-ui/react-scroll-area\": \"^1.1.0\",\n+    \"@radix-ui/react-select\": \"^2.1.1\",\n+    \"@radix-ui/react-separator\": \"^1.1.0\",\n+    \"@radix-ui/react-slider\": \"^1.2.0\",\n+    \"@radix-ui/react-slot\": \"^1.1.0\",\n+    \"@radix-ui/react-switch\": \"^1.1.0\",\n+    \"@radix-ui/react-tabs\": \"^1.1.0\",\n+    \"@radix-ui/react-toast\": \"^1.2.1\",\n+    \"@radix-ui/react-toggle\": \"^1.1.0\",\n+    \"@radix-ui/react-toggle-group\": \"^1.1.0\",\n+    \"@radix-ui/react-tooltip\": \"^1.1.4\",\n+    \"@supabase/supabase-js\": \"^2.50.0\",\n+    \"@tanstack/react-query\": \"^5.56.2\",\n+    \"class-variance-authority\": \"^0.7.1\",\n+    \"clsx\": \"^2.1.1\",\n+    \"cmdk\": \"^1.0.0\",\n+    \"crypto-js\": \"^4.2.0\",\n+    \"date-fns\": \"^3.6.0\",\n+    \"embla-carousel-react\": \"^8.3.0\",\n+    \"input-otp\": \"^1.2.4\",\n+    \"lucide-react\": \"^0.462.0\",\n+    \"next\": \"^15.0.0\",\n+    \"next-themes\": \"^0.3.0\",\n+    \"otplib\": \"^12.0.1\",\n+    \"react\": \"^18.3.1\",\n+    \"react-day-picker\": \"^8.10.1\",\n+    \"react-dom\": \"^18.3.1\",\n+    \"react-hook-form\": \"^7.53.0\",\n+    \"react-resizable-panels\": \"^2.1.3\",\n+    \"recharts\": \"^2.12.7\",\n+    \"sonner\": \"^1.5.0\",\n+    \"tailwind-merge\": \"^2.5.2\",\n+    \"tailwindcss-animate\": \"^1.0.7\",\n+    \"vaul\": \"^0.9.3\",\n+    \"zod\": \"^3.23.8\"\n+  },\n+  \"devDependencies\": {\n+    \"@tailwindcss/typography\": \"^0.5.15\",\n+    \"@types/node\": \"^22.5.5\",\n+    \"@types/react\": \"^18.3.3\",\n+    \"@types/react-dom\": \"^18.3.0\",\n+    \"autoprefixer\": \"^10.4.20\",\n+    \"eslint\": \"^9.9.0\",\n+    \"eslint-config-next\": \"^15.0.0\",\n+    \"gh-pages\": \"^6.3.0\",\n+    \"postcss\": \"^8.4.47\",\n+    \"tailwindcss\": \"^3.4.11\",\n+    \"typescript\": \"^5.5.3\"\n+  }\n+}\n"
                }
            ],
            "date": 1749928714177,
            "name": "Commit-0",
            "content": "{\n  \"name\": \"supauth\",\n  \"description\": \"Supauth - Open Source Authentication Kit with Next.js, React, Supabase, and shadcn/ui\",\n  \"version\": \"1.0.0\",\n  \"private\": false,\n  \"license\": \"MIT\",\n  \"repository\": {\n    \"type\": \"git\",\n    \"url\": \"https://github.com/asim1801/supa-auth-nextjs\"\n  },\n  \"homepage\": \"https://asim1801.github.io/supa-auth-nextjs\",\n  \"keywords\": [\n    \"authentication\",\n    \"nextjs\",\n    \"react\",\n    \"supabase\",\n    \"shadcn\",\n    \"open-source\",\n    \"typescript\",\n    \"tailwindcss\"\n  ],\n  \"author\": \"Supauth Contributors\",\n  \"scripts\": {\n    \"dev\": \"next dev\",\n    \"build\": \"next build\",\n    \"start\": \"next start\",\n    \"lint\": \"next lint\",\n    \"setup\": \"node scripts/setup.js\",\n    \"migrate\": \"npx supabase db push\",\n    \"db:generate-types\": \"npx supabase gen types typescript --local > src/types/database.types.ts\",\n    \"export\": \"next build && next export\",\n    \"deploy\": \"npm run build && gh-pages -d out\",\n    \"predeploy\": \"npm run build\",\n    \"postinstall\": \"echo '✅ Installation complete! Run npm run dev to start the development server.'\"\n  },\n  \"dependencies\": {\n    \"@hookform/resolvers\": \"^3.9.0\",\n    \"@radix-ui/react-accordion\": \"^1.2.0\",\n    \"@radix-ui/react-alert-dialog\": \"^1.1.1\",\n    \"@radix-ui/react-aspect-ratio\": \"^1.1.0\",\n    \"@radix-ui/react-avatar\": \"^1.1.0\",\n    \"@radix-ui/react-checkbox\": \"^1.1.1\",\n    \"@radix-ui/react-collapsible\": \"^1.1.0\",\n    \"@radix-ui/react-context-menu\": \"^2.2.1\",\n    \"@radix-ui/react-dialog\": \"^1.1.2\",\n    \"@radix-ui/react-dropdown-menu\": \"^2.1.1\",\n    \"@radix-ui/react-hover-card\": \"^1.1.1\",\n    \"@radix-ui/react-label\": \"^2.1.0\",\n    \"@radix-ui/react-menubar\": \"^1.1.1\",\n    \"@radix-ui/react-navigation-menu\": \"^1.2.0\",\n    \"@radix-ui/react-popover\": \"^1.1.1\",\n    \"@radix-ui/react-progress\": \"^1.1.0\",\n    \"@radix-ui/react-radio-group\": \"^1.2.0\",\n    \"@radix-ui/react-scroll-area\": \"^1.1.0\",\n    \"@radix-ui/react-select\": \"^2.1.1\",\n    \"@radix-ui/react-separator\": \"^1.1.0\",\n    \"@radix-ui/react-slider\": \"^1.2.0\",\n    \"@radix-ui/react-slot\": \"^1.1.0\",\n    \"@radix-ui/react-switch\": \"^1.1.0\",\n    \"@radix-ui/react-tabs\": \"^1.1.0\",\n    \"@radix-ui/react-toast\": \"^1.2.1\",\n    \"@radix-ui/react-toggle\": \"^1.1.0\",\n    \"@radix-ui/react-toggle-group\": \"^1.1.0\",\n    \"@radix-ui/react-tooltip\": \"^1.1.4\",\n    \"@supabase/supabase-js\": \"^2.50.0\",\n    \"@tanstack/react-query\": \"^5.56.2\",\n    \"class-variance-authority\": \"^0.7.1\",\n    \"clsx\": \"^2.1.1\",\n    \"cmdk\": \"^1.0.0\",\n    \"crypto-js\": \"^4.2.0\",\n    \"date-fns\": \"^3.6.0\",\n    \"embla-carousel-react\": \"^8.3.0\",\n    \"input-otp\": \"^1.2.4\",\n    \"lucide-react\": \"^0.462.0\",\n    \"next\": \"^15.0.0\",\n    \"next-themes\": \"^0.3.0\",\n    \"otplib\": \"^12.0.1\",\n    \"react\": \"^18.3.1\",\n    \"react-day-picker\": \"^8.10.1\",\n    \"react-dom\": \"^18.3.1\",\n    \"react-hook-form\": \"^7.53.0\",\n    \"react-resizable-panels\": \"^2.1.3\",\n    \"recharts\": \"^2.12.7\",\n    \"sonner\": \"^1.5.0\",\n    \"tailwind-merge\": \"^2.5.2\",\n    \"tailwindcss-animate\": \"^1.0.7\",\n    \"vaul\": \"^0.9.3\",\n    \"zod\": \"^3.23.8\"\n  },\n  \"devDependencies\": {\n    \"@tailwindcss/typography\": \"^0.5.15\",\n    \"@types/node\": \"^22.5.5\",\n    \"@types/react\": \"^18.3.3\",\n    \"@types/react-dom\": \"^18.3.0\",\n    \"autoprefixer\": \"^10.4.20\",\n    \"eslint\": \"^9.9.0\",\n    \"eslint-config-next\": \"^15.0.0\",\n    \"gh-pages\": \"^6.3.0\",\n    \"postcss\": \"^8.4.47\",\n    \"tailwindcss\": \"^3.4.11\",\n    \"typescript\": \"^5.5.3\"\n  }\n}\n"
        }
    ]
}